<?xml version="1.0" encoding="UTF-8"?>
<Export generator="Cache" version="25">
<Class name="Simple.REST.Broker">
<Super>%CSP.REST</Super>
<TimeCreated>64120,61301.79551</TimeCreated>

<XData name="UrlMap">
<Data><![CDATA[
<Routes>

<!-- Получить людей -->
<Route Url="/GetPersons" Method="GET" Call="Simple.Service.Person:GetPersons"/>
<Route Url="/GetStatuses" Method="GET" Call="Simple.Service.Status:GetStatuses"/>

<Route Url="/person/:id" Method="GET" Call="Simple.Service.Person:Get"/>
<Route Url="/person/save" Method="POST" Call="Simple.Service.Person:Save"/>
<Route Url="/person/:id" Method="DELETE" Call="Simple.Service.Person:Delete"/>

</Routes>
]]></Data>
</XData>
</Class>
</Export>
